fucknuker/__init__.py
fucknuker/main.py
fuckyoubitch-0.1.1.dist-info/METADATA
fuckyoubitch-0.1.1.dist-info/WHEEL
fuckyoubitch-0.1.1.dist-info/entry_points.txt
fuckyoubitch-0.1.1.dist-info/top_level.txt
fuckyoubitch-0.1.1.dist-info/RECORD
