Metadata-Version: 2.4
Name: fuckyoubitch
Version: 0.1.1
Summary: مكتبة لتحميل وتشغيل ملف exe من رابط
Author: اسمك
Requires-Python: >=3.10
Dynamic: author
Dynamic: requires-python
Dynamic: summary
